flask_livereload/__init__.py
flask_livereload/views.py
flask_livereload-0.2.1.dist-info/licenses/LICENSE
flask_livereload-0.2.1.dist-info/METADATA
flask_livereload-0.2.1.dist-info/WHEEL
flask_livereload-0.2.1.dist-info/top_level.txt
flask_livereload-0.2.1.dist-info/RECORD
