Metadata-Version: 2.4
Name: Flask-LiveReload
Version: 0.2.1
Summary: Live reloading for Flask applications during development.
Author-email: Hernan Varillas <hernan.varillas93@gmail.com>
License-Expression: MIT
Project-URL: Homepage, https://github.com/hvarillas/flask-livereload
Project-URL: Bug Tracker, https://github.com/hvarillas/flask-livereload/issues
Keywords: flask,livereload,auto-reload,development,watchdog
Classifier: Development Status :: 4 - Beta
Classifier: Environment :: Web Environment
Classifier: Framework :: Flask
Classifier: Intended Audience :: Developers
Classifier: Operating System :: OS Independent
Classifier: Programming Language :: Python
Classifier: Programming Language :: Python :: 3
Classifier: Programming Language :: Python :: 3.8
Classifier: Programming Language :: Python :: 3.9
Classifier: Programming Language :: Python :: 3.10
Classifier: Programming Language :: Python :: 3.11
Classifier: Programming Language :: Python :: 3.12
Classifier: Topic :: Internet :: WWW/HTTP :: Dynamic Content
Classifier: Topic :: Software Development :: Libraries :: Python Modules
Requires-Python: >=3.8
License-File: LICENSE
Requires-Dist: Flask>=2.0
Requires-Dist: watchdog
Dynamic: license-file
